prodia_api/__init__.py
prodia_api/_prodia.py
prodia_api/enums.py
prodia_api-0.1.1.dist-info/LICENSE
prodia_api-0.1.1.dist-info/METADATA
prodia_api-0.1.1.dist-info/WHEEL
prodia_api-0.1.1.dist-info/RECORD
